quantem/__init__.py
quantem/core/__init__.py
quantem/core/config.py
quantem/core/quantem.yaml
quantem/core/datastructures/__init__.py
quantem/core/datastructures/dataset.py
quantem/core/datastructures/dataset2d.py
quantem/core/datastructures/dataset3d.py
quantem/core/datastructures/dataset4d.py
quantem/core/datastructures/dataset4dstem.py
quantem/core/datastructures/vector.py
quantem/core/io/__init__.py
quantem/core/io/file_readers.py
quantem/core/io/serialize.py
quantem/core/ml/__init__.py
quantem/core/ml/activation_functions.py
quantem/core/ml/blocks.py
quantem/core/ml/cnn.py
quantem/core/ml/cnn_dense.py
quantem/core/ml/conv_autoencoder.py
quantem/core/ml/dense_nn.py
quantem/core/ml/inr.py
quantem/core/ml/logger.py
quantem/core/ml/loss_functions.py
quantem/core/ml/optimizer_mixin.py
quantem/core/ml/splat/__init__.py
quantem/core/ml/splat/datasets.py
quantem/core/ml/splat/gs.py
quantem/core/ml/splat/gs_config.py
quantem/core/ml/splat/gs_rendering.py
quantem/core/ml/splat/gs_strategy.py
quantem/core/ml/splat/gs_strategy_base.py
quantem/core/ml/splat/splat_base.py
quantem/core/ml/splat/splat_constraints.py
quantem/core/ml/splat/splat_tomo.py
quantem/core/utils/__init__.py
quantem/core/utils/array_funcs.py
quantem/core/utils/augment_dp.py
quantem/core/utils/compound_validators.py
quantem/core/utils/diffractive_imaging_utils.py
quantem/core/utils/filter.py
quantem/core/utils/imaging_utils.py
quantem/core/utils/rng.py
quantem/core/utils/utils.py
quantem/core/utils/validators.py
quantem/core/visualization/__init__.py
quantem/core/visualization/custom_normalizations.py
quantem/core/visualization/line_scan.py
quantem/core/visualization/visualization.py
quantem/core/visualization/visualization_utils.py
quantem/diffraction/__init__.py
quantem/diffractive_imaging/__init__.py
quantem/diffractive_imaging/complex_probe.py
quantem/diffractive_imaging/constraints.py
quantem/diffractive_imaging/dataset_models.py
quantem/diffractive_imaging/detector_models.py
quantem-0.1.8.dist-info/METADATA
quantem-0.1.8.dist-info/WHEEL
quantem-0.1.8.dist-info/licenses/LICENSE
quantem-0.1.8.dist-info/RECORD
